thalesians/__init__.py
thalesians/tsa/__init__.py
thalesians/tsa/checks.py
thalesians/tsa/conditions.py
thalesians/tsa/conversions.py
thalesians/tsa/distrs.py
thalesians/tsa/evaluation.py
thalesians/tsa/exceptions.py
thalesians/tsa/finance.py
thalesians/tsa/intervals.py
thalesians/tsa/jupyterutils.py
thalesians/tsa/kde.py
thalesians/tsa/numpychecks.py
thalesians/tsa/numpyutils.py
thalesians/tsa/objects.py
thalesians/tsa/outliers.py
thalesians/tsa/pandasutils.py
thalesians/tsa/processes.py
thalesians/tsa/pypes.py
thalesians/tsa/random.py
thalesians/tsa/randomness.py
thalesians/tsa/settings.py
thalesians/tsa/signatures.py
thalesians/tsa/simulation.py
thalesians/tsa/stats.py
thalesians/tsa/strings.py
thalesians/tsa/timeconsts.py
thalesians/tsa/times.py
thalesians/tsa/tsa.py
thalesians/tsa/tsa_settings.py
thalesians/tsa/utils.py
thalesians/tsa/visual.py
thalesians/tsa/datasets/__init__.py
thalesians/tsa/datasets/finratrace.py
thalesians/tsa/filtering/__init__.py
thalesians/tsa/filtering/kalman.py
thalesians/tsa/filtering/particle.py
thalesians/tsa/filtering/visual.py
thalesians/tsa/neural/__init__.py
thalesians/tsa/neural/tfwrapper.py
thalesians/tsa/optimisation/__init__.py
thalesians/tsa/optimisation/visual.py
thalesians/tsa/optimization/__init__.py
thalesians/tsa/optimization/visual.py
thalesians/tsa/q/__init__.py
thalesians/tsa/q/q2.py
thalesians/tsa/q/q3.py
thalesians/tsa/q/qutils.py
thalesians.tsa-0.5.dist-info/METADATA
thalesians.tsa-0.5.dist-info/WHEEL
thalesians.tsa-0.5.dist-info/top_level.txt
thalesians.tsa-0.5.dist-info/RECORD
