Metadata-Version: 2.1
Name: thalesians.tsa
Version: 0.5
Summary: The Thalesians' Time Series Analysis (TSA) library
Home-page: https://github.com/thalesians/tsa
Author: Thalesians Ltd
Author-email: info@thalesians.com
License: Apache-2.0
Platform: UNKNOWN
